rtl/conflict_table.sv
module conflict_table
# ( parameter DEPTH = 8,
    parameter DATA_WIDTH = 64,
    parameter HASH_WIDTH = 12 
  ) 
  ( input clk,
    input rst,
    input cs,
    input we,
    output match,
    input [DATA_WIDTH-1:0] data,
    input [HASH_WIDTH-1:0] hash_in,
    input [HASH_WIDTH-1:0] map_in,
    output [HASH_WIDTH-1:0] hash_out,
    output [HASH_WIDTH-1:0] map_out,
    output ct_full
  );

  reg [HASH_WIDTH-1:0] tmp_hash;
  reg [HASH_WIDTH-1:0] tmp_map;
  reg [DATA_WIDTH-1:0] mem_data [DEPTH];
  reg [HASH_WIDTH-1:0] mem_hash [DEPTH];
  reg [HASH_WIDTH-1:0] mem_map [DEPTH];
  wire [DEPTH-1:0] match_wires;
  reg [HASH_WIDTH-1:0] counter;
  wire [7:0] encoder_in;
  wire [2:0] encoder_out;
/*
// Generate wires for matching
  genvar i;
  generate
    for (i = 0; i < DEPTH; i++) begin : match_gen
      wire match_wire;
      assign match_wire = (cs && !we && (data == mem_data[i]));
      assign match_regs[i] = match_wire;
    end
  endgenerate
*/

// Match wires
  assign  match_wires[7] = ((data == mem_data[7]) && (data != 0)) ? 1'b1 : 1'b0;
  assign  match_wires[6] = ((data == mem_data[6]) && (data != 0)) ? 1'b1 : 1'b0;
  assign  match_wires[5] = ((data == mem_data[5]) && (data != 0)) ? 1'b1 : 1'b0;
  assign  match_wires[4] = ((data == mem_data[4]) && (data != 0)) ? 1'b1 : 1'b0;
  assign  match_wires[3] = ((data == mem_data[3]) && (data != 0)) ? 1'b1 : 1'b0;
  assign  match_wires[2] = ((data == mem_data[2]) && (data != 0)) ? 1'b1 : 1'b0;
  assign  match_wires[1] = ((data == mem_data[1]) && (data != 0)) ? 1'b1 : 1'b0;
  assign  match_wires[0] = ((data == mem_data[0]) && (data != 0)) ? 1'b1 : 1'b0;

// Encoder logic
  assign encoder_out[2] = encoder_in[4] | encoder_in[5] | encoder_in[6] | encoder_in[7];
  assign encoder_out[1] = encoder_in[2] | encoder_in[3] | encoder_in[6] | encoder_in[7];
  assign encoder_out[0] = encoder_in[1] | encoder_in[3] | encoder_in[5] | encoder_in[7];

  initial begin
    counter <= 0;
    mem_data[7] <= 0;
    mem_data[6] <= 0;
    mem_data[5] <= 0;
    mem_data[4] <= 0;
    mem_data[3] <= 0;
    mem_data[2] <= 0;
    mem_data[1] <= 0;
    mem_data[0] <= 0;
  end

  always @ (posedge clk) begin
    if (!rst) begin // Active LOW reset
	counter <= 0;
	mem_data[7] <= 0;
	mem_data[6] <= 0;
	mem_data[5] <= 0;
	mem_data[4] <= 0;
	mem_data[3] <= 0;
	mem_data[2] <= 0;
	mem_data[1] <= 0;
	mem_data[0] <= 0;
    end
// Writing entry into conflict table
    else if (cs & we & rst) begin
	mem_data[counter] <= data;
	mem_hash[counter] <= hash_in;
	mem_map[counter] <= map_in;
	if (counter != 3'b111)
	  counter <= counter + 1;
    end
// Getting entry from conflict table
    else if (cs & !we & rst) begin
	tmp_hash <= mem_hash[encoder_out];
	tmp_map <= mem_map[encoder_out];
    end
  end
	  	
// Assert match when any of the data cells match the input
  assign match = (|(match_wires) & cs);
// The match regs feed into the encoder
  assign encoder_in[7:0] = match_wires[7:0];
// Hash output
  assign hash_out = cs & !we ? tmp_hash : 'hz;
// Map output
  assign map_out = cs & !we ? tmp_map : 'hz;
// If the counter is at 8, the conflict table is full
  assign ct_full = (counter == 3'b111) ? 1 : 0;

endmodule

rtl/testbench/conflict_table_tb.sv
module conflict_table_tb;

  // Parameters
  parameter DEPTH = 16;
  parameter DATA_WIDTH = 64;
  parameter HASH_WIDTH = 12;

  // Signals
  reg clk, rst, cs, we, ct_full;
  reg [DATA_WIDTH-1:0] data;
  reg [HASH_WIDTH-1:0] hash_in, map_in;
  wire match;
  wire [HASH_WIDTH-1:0] hash_out;

  // Instantiate the conflict_table module
  conflict_table #(DEPTH, DATA_WIDTH, HASH_WIDTH) uut (
    .clk(clk),
    .rst(rst),
    .cs(cs),
    .we(we),
    .match(match),
    .data(data),
    .hash_in(hash_in),
    .map_in(map_in),
    .hash_out(hash_out),
    .ct_full(ct_full)
  );

  // Clock generation
  always #5 clk = ~clk;

  // Initial values
  initial begin
    $dumpfile("conflict_table_tb.vcd");
    $dumpvars(0, conflict_table_tb);
    clk = 0;
    rst = 0;
    cs = 0;
    we = 0;
    data = 64'h0000000000000000;
    hash_in = 12'h000;
  // Testing
    #15 rst = 1; cs = 1; we = 1;
    data = 64'h1122334455667788;
    hash_in = 12'h123;
    map_in = 12'h321;
    #10 data = 64'h8877665544332211; hash_in = 12'h321;
    #10 data = 64'h2222222222222222; hash_in = 12'h222;
    #10 data = 64'h3333333333333333; hash_in = 12'h333;
    #10 data = 64'h4444444444444444; hash_in = 12'h444;
    #10 data = 64'h5555555555555555; hash_in = 12'h555;
    #10 data = 64'h6666666666666666; hash_in = 12'h666;
    #10 data = 64'h7777777777777777; hash_in = 12'h777;

    #10 data = 64'h8888888888888888; hash_in = 12'h888;
    #10 data = 64'hAAAAAAAAAAAAAAAA; hash_in = 12'h999;
    #10 data = 64'hBBBBBBBBBBBBBBBB; hash_in = 12'hAAA;
    #10 data = 64'hCCCCCCCCCCCCCCCC; hash_in = 12'hBBB;
    #10 data = 64'hDDDDDDDDDDDDDDDD; hash_in = 12'hCCC;
    #10 data = 64'hEEEEEEEEEEEEEEEE; hash_in = 12'hDDD;
    #10 data = 64'hFFFFFFFFFFFFFFFF; hash_in = 12'hEEE;
    #10 data = 64'h1111111111111111; hash_in = 12'h111;

    #10 cs = 1;
    #10 we = 0;

    #10 data = 64'h7777777777777777; hash_in = 12'h777;
    #10 data = 64'h6666666666666666; hash_in = 12'h666;
    #10 data = 64'h5555555555555555; hash_in = 12'h555;
    #10 data = 64'h4444444444444444; hash_in = 12'h444;
    #10 data = 64'h3333333333333333; hash_in = 12'h333;
    #10 data = 64'h2222222222222222; hash_in = 12'h222;
    #10 data = 64'h8877665544332211; hash_in = 12'h321;
    #10 data = 64'h1122334455667788; hash_in = 12'h123;

    #10 data = 64'h8888888888888888; hash_in = 12'h888;
    #10 data = 64'hAAAAAAAAAAAAAAAA; hash_in = 12'h999;
    #10 data = 64'hBBBBBBBBBBBBBBBB; hash_in = 12'hAAA;
    #10 data = 64'hCCCCCCCCCCCCCCCC; hash_in = 12'hBBB;
    #10 data = 64'hDDDDDDDDDDDDDDDD; hash_in = 12'hCCC;
    #10 data = 64'hEEEEEEEEEEEEEEEE; hash_in = 12'hDDD;
    #10 data = 64'hFFFFFFFFFFFFFFFF; hash_in = 12'hEEE;
    #10 data = 64'h1111111111111111; hash_in = 12'h111;

    #20
    $stop;
    
  end

  // Monitor
  always @(posedge clk) begin
    $display("Time %0t: Match = %b", $time, match);
  end

endmodule

rtl/conflict_table_tb.vcd
$date
	Tue Apr 16 13:54:18 2024
$end
$version
	ModelSim Version 10.5b
$end
$timescale
	1ps
$end

$scope module conflict_table_tb $end
$var parameter 32 ! DEPTH $end
$var parameter 32 " DATA_WIDTH $end
$var parameter 32 # HASH_WIDTH $end
$var reg 1 $ clk $end
$var reg 1 % rst $end
$var reg 1 & cs $end
$var reg 1 ' we $end
$var reg 1 ( ct_full $end
$var reg 64 ) data [63:0] $end
$var reg 12 * hash_in [11:0] $end
$var reg 12 + map_in [11:0] $end
$var wire 1 , match $end
$var wire 1 - hash_out [11] $end
$var wire 1 . hash_out [10] $end
$var wire 1 / hash_out [9] $end
$var wire 1 0 hash_out [8] $end
$var wire 1 1 hash_out [7] $end
$var wire 1 2 hash_out [6] $end
$var wire 1 3 hash_out [5] $end
$var wire 1 4 hash_out [4] $end
$var wire 1 5 hash_out [3] $end
$var wire 1 6 hash_out [2] $end
$var wire 1 7 hash_out [1] $end
$var wire 1 8 hash_out [0] $end

$scope module uut $end
$var parameter 32 9 DEPTH $end
$var parameter 32 : DATA_WIDTH $end
$var parameter 32 ; HASH_WIDTH $end
$var wire 1 < clk $end
$var wire 1 = rst $end
$var wire 1 > cs $end
$var wire 1 ? we $end
$var wire 1 , match $end
$var wire 1 @ data [63] $end
$var wire 1 A data [62] $end
$var wire 1 B data [61] $end
$var wire 1 C data [60] $end
$var wire 1 D data [59] $end
$var wire 1 E data [58] $end
$var wire 1 F data [57] $end
$var wire 1 G data [56] $end
$var wire 1 H data [55] $end
$var wire 1 I data [54] $end
$var wire 1 J data [53] $end
$var wire 1 K data [52] $end
$var wire 1 L data [51] $end
$var wire 1 M data [50] $end
$var wire 1 N data [49] $end
$var wire 1 O data [48] $end
$var wire 1 P data [47] $end
$var wire 1 Q data [46] $end
$var wire 1 R data [45] $end
$var wire 1 S data [44] $end
$var wire 1 T data [43] $end
$var wire 1 U data [42] $end
$var wire 1 V data [41] $end
$var wire 1 W data [40] $end
$var wire 1 X data [39] $end
$var wire 1 Y data [38] $end
$var wire 1 Z data [37] $end
$var wire 1 [ data [36] $end
$var wire 1 \ data [35] $end
$var wire 1 ] data [34] $end
$var wire 1 ^ data [33] $end
$var wire 1 _ data [32] $end
$var wire 1 ` data [31] $end
$var wire 1 a data [30] $end
$var wire 1 b data [29] $end
$var wire 1 c data [28] $end
$var wire 1 d data [27] $end
$var wire 1 e data [26] $end
$var wire 1 f data [25] $end
$var wire 1 g data [24] $end
$var wire 1 h data [23] $end
$var wire 1 i data [22] $end
$var wire 1 j data [21] $end
$var wire 1 k data [20] $end
$var wire 1 l data [19] $end
$var wire 1 m data [18] $end
$var wire 1 n data [17] $end
$var wire 1 o data [16] $end
$var wire 1 p data [15] $end
$var wire 1 q data [14] $end
$var wire 1 r data [13] $end
$var wire 1 s data [12] $end
$var wire 1 t data [11] $end
$var wire 1 u data [10] $end
$var wire 1 v data [9] $end
$var wire 1 w data [8] $end
$var wire 1 x data [7] $end
$var wire 1 y data [6] $end
$var wire 1 z data [5] $end
$var wire 1 { data [4] $end
$var wire 1 | data [3] $end
$var wire 1 } data [2] $end
$var wire 1 ~ data [1] $end
$var wire 1 !! data [0] $end
$var wire 1 "! hash_in [11] $end
$var wire 1 #! hash_in [10] $end
$var wire 1 $! hash_in [9] $end
$var wire 1 %! hash_in [8] $end
$var wire 1 &! hash_in [7] $end
$var wire 1 '! hash_in [6] $end
$var wire 1 (! hash_in [5] $end
$var wire 1 )! hash_in [4] $end
$var wire 1 *! hash_in [3] $end
$var wire 1 +! hash_in [2] $end
$var wire 1 ,! hash_in [1] $end
$var wire 1 -! hash_in [0] $end
$var wire 1 .! map_in [11] $end
$var wire 1 /! map_in [10] $end
$var wire 1 0! map_in [9] $end
$var wire 1 1! map_in [8] $end
$var wire 1 2! map_in [7] $end
$var wire 1 3! map_in [6] $end
$var wire 1 4! map_in [5] $end
$var wire 1 5! map_in [4] $end
$var wire 1 6! map_in [3] $end
$var wire 1 7! map_in [2] $end
$var wire 1 8! map_in [1] $end
$var wire 1 9! map_in [0] $end
$var wire 1 - hash_out [11] $end
$var wire 1 . hash_out [10] $end
$var wire 1 / hash_out [9] $end
$var wire 1 0 hash_out [8] $end
$var wire 1 1 hash_out [7] $end
$var wire 1 2 hash_out [6] $end
$var wire 1 3 hash_out [5] $end
$var wire 1 4 hash_out [4] $end
$var wire 1 5 hash_out [3] $end
$var wire 1 6 hash_out [2] $end
$var wire 1 7 hash_out [1] $end
$var wire 1 8 hash_out [0] $end
$var wire 1 :! map_out [11] $end
$var wire 1 ;! map_out [10] $end
$var wire 1 <! map_out [9] $end
$var wire 1 =! map_out [8] $end
$var wire 1 >! map_out [7] $end
$var wire 1 ?! map_out [6] $end
$var wire 1 @! map_out [5] $end
$var wire 1 A! map_out [4] $end
$var wire 1 B! map_out [3] $end
$var wire 1 C! map_out [2] $end
$var wire 1 D! map_out [1] $end
$var wire 1 E! map_out [0] $end
$var wire 1 F! ct_full $end
$var reg 12 G! tmp_hash [11:0] $end
$var reg 12 H! tmp_map [11:0] $end
$var wire 1 I! match_wires [15] $end
$var wire 1 J! match_wires [14] $end
$var wire 1 K! match_wires [13] $end
$var wire 1 L! match_wires [12] $end
$var wire 1 M! match_wires [11] $end
$var wire 1 N! match_wires [10] $end
$var wire 1 O! match_wires [9] $end
$var wire 1 P! match_wires [8] $end
$var wire 1 Q! match_wires [7] $end
$var wire 1 R! match_wires [6] $end
$var wire 1 S! match_wires [5] $end
$var wire 1 T! match_wires [4] $end
$var wire 1 U! match_wires [3] $end
$var wire 1 V! match_wires [2] $end
$var wire 1 W! match_wires [1] $end
$var wire 1 X! match_wires [0] $end
$var reg 5 Y! counter [4:0] $end
$var wire 1 Z! encoder_in [15] $end
$var wire 1 [! encoder_in [14] $end
$var wire 1 \! encoder_in [13] $end
$var wire 1 ]! encoder_in [12] $end
$var wire 1 ^! encoder_in [11] $end
$var wire 1 _! encoder_in [10] $end
$var wire 1 `! encoder_in [9] $end
$var wire 1 a! encoder_in [8] $end
$var wire 1 b! encoder_in [7] $end
$var wire 1 c! encoder_in [6] $end
$var wire 1 d! encoder_in [5] $end
$var wire 1 e! encoder_in [4] $end
$var wire 1 f! encoder_in [3] $end
$var wire 1 g! encoder_in [2] $end
$var wire 1 h! encoder_in [1] $end
$var wire 1 i! encoder_in [0] $end
$var wire 1 j! encoder_out [3] $end
$var wire 1 k! encoder_out [2] $end
$var wire 1 l! encoder_out [1] $end
$var wire 1 m! encoder_out [0] $end

$scope begin genblk1 $end
$upscope $end

$scope begin genblk2 $end
$upscope $end

$scope begin genblk3 $end
$upscope $end
$upscope $end
$upscope $end
$enddefinitions $end
#0
$dumpvars
0$
0%
0&
0'
0(
b0 )
b0 *
bx +
b0 G!
b0 H!
b0 Y!
b10000 !
b1000000 "
b1100 #
b10000 9
b1000000 :
b1100 ;
0,
z8
z7
z6
z5
z4
z3
z2
z1
z0
z/
z.
z-
0X!
0W!
0V!
0U!
0T!
0S!
0R!
0Q!
0P!
0O!
0N!
0M!
0L!
0K!
0J!
0I!
0i!
0h!
0g!
0f!
0e!
0d!
0c!
0b!
0a!
0`!
0_!
0^!
0]!
0\!
0[!
0Z!
0m!
0l!
0k!
0j!
0<
0=
0>
0?
0!!
0~
0}
0|
0{
0z
0y
0x
0w
0v
0u
0t
0s
0r
0q
0p
0o
0n
0m
0l
0k
0j
0i
0h
0g
0f
0e
0d
0c
0b
0a
0`
0_
0^
0]
0\
0[
0Z
0Y
0X
0W
0V
0U
0T
0S
0R
0Q
0P
0O
0N
0M
0L
0K
0J
0I
0H
0G
0F
0E
0D
0C
0B
0A
0@
0-!
0,!
0+!
0*!
0)!
0(!
0'!
0&!
0%!
0$!
0#!
0"!
x9!
x8!
x7!
x6!
x5!
x4!
x3!
x2!
x1!
x0!
x/!
x.!
0F!
zE!
zD!
zC!
zB!
zA!
z@!
z?!
z>!
z=!
z<!
z;!
z:!
$end
#5
1$
1<
#10
0$
0<
#15
1%
1&
1'
b1000100100010001100110100010001010101011001100111011110001000 )
b100100011 *
b1100100001 +
1$
1=
1>
1?
19!
08!
07!
06!
05!
14!
03!
02!
11!
10!
0/!
0.!
1-!
1,!
1(!
1%!
1|
1x
1w
1v
1u
1s
1r
1q
1n
1m
1j
1i
1g
1e
1c
1a
1]
1Y
1W
1V
1S
1R
1N
1J
1G
1C
1<
b1 Y!
1X!
1i!
1,
b100100011 G!
b1100100001 H!
#20
0$
0<
#25
b1000100001110111011001100101010101000100001100110010001000010001 )
b1100100001 *
1$
0,!
1$!
1!!
0|
1{
0x
0w
0u
0s
0q
1o
0m
1k
0i
0g
0c
1_
1[
0W
1U
0S
1Q
1O
1M
1K
1I
0G
1D
0C
1@
0X!
0i!
1<
0,
b10 Y!
1W!
1h!
1,
1m!
b1100100001 G!
#30
0$
0<
#35
b10001000100010001000100010001000100010001000100010001000100010 )
b1000100010 *
1$
0-!
1,!
0%!
0!!
1~
0{
1z
0o
0k
1f
0e
1b
0a
0_
1^
0]
0[
1Z
0Y
0U
0Q
0O
0M
0K
0I
1F
0D
1B
0@
0W!
0h!
1<
0,
0m!
b100100011 G!
b11 Y!
1V!
1g!
1,
1l!
b1000100010 G!
#40
0$
0<
#45
b11001100110011001100110011001100110011001100110011001100110011 )
b1100110011 *
1$
1-!
1)!
1%!
1!!
1{
1w
1s
1o
1k
1g
1c
1_
1[
1W
1S
1O
1K
1G
1C
0V!
0g!
1<
0,
0l!
b100100011 G!
b100 Y!
1U!
1f!
1,
1m!
1l!
b1100110011 G!
#50
0$
0<
#55
b100010001000100010001000100010001000100010001000100010001000100 )
b10001000100 *
1$
0-!
0,!
1+!
0)!
0(!
1'!
0%!
0$!
1#!
0!!
0~
1}
0{
0z
1y
0w
0v
1u
0s
0r
1q
0o
0n
1m
0k
0j
1i
0g
0f
1e
0c
0b
1a
0_
0^
1]
0[
0Z
1Y
0W
0V
1U
0S
0R
1Q
0O
0N
1M
0K
0J
1I
0G
0F
1E
0C
0B
1A
0U!
0f!
1<
0,
0m!
0l!
b100100011 G!
b101 Y!
1T!
1e!
1,
1k!
b10001000100 G!
#60
0$
0<
#65
b101010101010101010101010101010101010101010101010101010101010101 )
b10101010101 *
1$
1-!
1)!
1%!
1!!
1{
1w
1s
1o
1k
1g
1c
1_
1[
1W
1S
1O
1K
1G
1C
0T!
0e!
1<
0,
0k!
b100100011 G!
b110 Y!
1S!
1d!
1,
1m!
1k!
b10101010101 G!
#70
0$
0<
#75
b110011001100110011001100110011001100110011001100110011001100110 )
b11001100110 *
1$
0-!
1,!
0)!
1(!
0%!
1$!
0!!
1~
0{
1z
0w
1v
0s
1r
0o
1n
0k
1j
0g
1f
0c
1b
0_
1^
0[
1Z
0W
1V
0S
1R
0O
1N
0K
1J
0G
1F
0C
1B
0S!
0d!
1<
0,
0m!
0k!
b100100011 G!
b111 Y!
1R!
1c!
1,
1l!
1k!
b11001100110 G!
#80
0$
0<
#85
b111011101110111011101110111011101110111011101110111011101110111 )
b11101110111 *
1$
1-!
1)!
1%!
1!!
1{
1w
1s
1o
1k
1g
1c
1_
1[
1W
1S
1O
1K
1G
1C
0R!
0c!
1<
0,
0l!
0k!
b100100011 G!
b1000 Y!
1Q!
1b!
1,
1m!
1l!
1k!
b11101110111 G!
#90
0$
0<
#95
b1000100010001000100010001000100010001000100010001000100010001000 )
b100010001000 *
1$
0-!
0,!
0+!
1*!
0)!
0(!
0'!
1&!
0%!
0$!
0#!
1"!
0!!
0~
0}
1|
0{
0z
0y
1x
0w
0v
0u
1t
0s
0r
0q
1p
0o
0n
0m
1l
0k
0j
0i
1h
0g
0f
0e
1d
0c
0b
0a
1`
0_
0^
0]
1\
0[
0Z
0Y
1X
0W
0V
0U
1T
0S
0R
0Q
1P
0O
0N
0M
1L
0K
0J
0I
1H
0G
0F
0E
1D
0C
0B
0A
1@
0Q!
0b!
1<
0,
0m!
0l!
0k!
b100100011 G!
b1001 Y!
1P!
1a!
1,
1j!
b100010001000 G!
#100
0$
0<
#105
b1010101010101010101010101010101010101010101010101010101010101010 )
b100110011001 *
1$
1-!
1)!
1%!
1~
1z
1v
1r
1n
1j
1f
1b
1^
1Z
1V
1R
1N
1J
1F
1B
0P!
0a!
1<
0,
0j!
b100100011 G!
b1010 Y!
1O!
1`!
1,
1m!
1j!
b100110011001 G!
#110
0$
0<
#115
b1011101110111011101110111011101110111011101110111011101110111011 )
b101010101010 *
1$
0-!
1,!
0)!
1(!
0%!
1$!
1!!
1{
1w
1s
1o
1k
1g
1c
1_
1[
1W
1S
1O
1K
1G
1C
0O!
0`!
1<
0,
0m!
0j!
b100100011 G!
b1011 Y!
1N!
1_!
1,
1l!
1j!
b101010101010 G!
#120
0$
0<
#125
b1100110011001100110011001100110011001100110011001100110011001100 )
b101110111011 *
1$
1-!
1)!
1%!
0!!
0~
1}
0{
0z
1y
0w
0v
1u
0s
0r
1q
0o
0n
1m
0k
0j
1i
0g
0f
1e
0c
0b
1a
0_
0^
1]
0[
0Z
1Y
0W
0V
1U
0S
0R
1Q
0O
0N
1M
0K
0J
1I
0G
0F
1E
0C
0B
1A
0N!
0_!
1<
0,
0l!
0j!
b100100011 G!
b1100 Y!
1M!
1^!
1,
1m!
1l!
1j!
b101110111011 G!
#130
0$
0<
#135
b1101110111011101110111011101110111011101110111011101110111011101 )
b110011001100 *
1$
0-!
0,!
1+!
0)!
0(!
1'!
0%!
0$!
1#!
1!!
1{
1w
1s
1o
1k
1g
1c
1_
1[
1W
1S
1O
1K
1G
1C
0M!
0^!
1<
0,
0m!
0l!
0j!
b100100011 G!
b1101 Y!
1L!
1]!
1,
1k!
1j!
b110011001100 G!
#140
0$
0<
#145
b1110111011101110111011101110111011101110111011101110111011101110 )
b110111011101 *
1$
1-!
1)!
1%!
0!!
1~
0{
1z
0w
1v
0s
1r
0o
1n
0k
1j
0g
1f
0c
1b
0_
1^
0[
1Z
0W
1V
0S
1R
0O
1N
0K
1J
0G
1F
0C
1B
0L!
0]!
1<
0,
0k!
0j!
b100100011 G!
b1110 Y!
1K!
1\!
1,
1m!
1k!
1j!
b110111011101 G!
#150
0$
0<
#155
b1111111111111111111111111111111111111111111111111111111111111111 )
b111011101110 *
1$
0-!
1,!
0)!
1(!
0%!
1$!
1!!
1{
1w
1s
1o
1k
1g
1c
1_
1[
1W
1S
1O
1K
1G
1C
0K!
0\!
1<
0,
0m!
0k!
0j!
b100100011 G!
b1111 Y!
1J!
1[!
1,
1l!
1k!
1j!
b111011101110 G!
#160
0$
0<
#165
b1000100010001000100010001000100010001000100010001000100010001 )
b100010001 *
1$
1-!
0,!
0+!
0*!
1)!
0(!
0'!
0&!
1%!
0$!
0#!
0"!
0~
0}
0|
0z
0y
0x
0v
0u
0t
0r
0q
0p
0n
0m
0l
0j
0i
0h
0f
0e
0d
0b
0a
0`
0^
0]
0\
0Z
0Y
0X
0V
0U
0T
0R
0Q
0P
0N
0M
0L
0J
0I
0H
0F
0E
0D
0B
0A
0@
0J!
0[!
1<
0,
0l!
0k!
0j!
b100100011 G!
b10000 Y!
1F!
1I!
1(
1Z!
1,
1m!
1l!
1k!
1j!
b100010001 G!
#170
0$
0<
#175
1$
1<
#180
0$
0<
#185
0'
1$
0?
18
07
06
05
14
03
02
01
10
0/
0.
0-
1E!
0D!
0C!
0B!
0A!
1@!
0?!
0>!
1=!
1<!
0;!
0:!
1<
#190
0$
0<
#195
b111011101110111011101110111011101110111011101110111011101110111 )
b11101110111 *
1$
1,!
1+!
1(!
1'!
1$!
1#!
1~
1}
1z
1y
1v
1u
1r
1q
1n
1m
1j
1i
1f
1e
1b
1a
1^
1]
1Z
1Y
1V
1U
1R
1Q
1N
1M
1J
1I
1F
1E
1B
1A
1Q!
0I!
1b!
0Z!
1<
0j!
b11101110111 G!
17
16
13
12
1/
1.
#200
0$
0<
#205
b110011001100110011001100110011001100110011001100110011001100110 )
b11001100110 *
1$
0-!
0)!
0%!
0!!
0{
0w
0s
0o
0k
0g
0c
0_
0[
0W
0S
0O
0K
0G
0C
1R!
0Q!
1c!
0b!
1<
0m!
b11001100110 G!
08
04
00
#210
0$
0<
#215
b101010101010101010101010101010101010101010101010101010101010101 )
b10101010101 *
1$
1-!
0,!
1)!
0(!
1%!
0$!
1!!
0~
1{
0z
1w
0v
1s
0r
1o
0n
1k
0j
1g
0f
1c
0b
1_
0^
1[
0Z
1W
0V
1S
0R
1O
0N
1K
0J
1G
0F
1C
0B
1S!
0R!
1d!
0c!
1<
1m!
0l!
b10101010101 G!
18
07
14
03
10
0/
#220
0$
0<
#225
b100010001000100010001000100010001000100010001000100010001000100 )
b10001000100 *
1$
0-!
0)!
0%!
0!!
0{
0w
0s
0o
0k
0g
0c
0_
0[
0W
0S
0O
0K
0G
0C
1T!
0S!
1e!
0d!
1<
0m!
b10001000100 G!
08
04
00
#230
0$
0<
#235
b11001100110011001100110011001100110011001100110011001100110011 )
b1100110011 *
1$
1-!
1,!
0+!
1)!
1(!
0'!
1%!
1$!
0#!
1!!
1~
0}
1{
1z
0y
1w
1v
0u
1s
1r
0q
1o
1n
0m
1k
1j
0i
1g
1f
0e
1c
1b
0a
1_
1^
0]
1[
1Z
0Y
1W
1V
0U
1S
1R
0Q
1O
1N
0M
1K
1J
0I
1G
1F
0E
1C
1B
0A
1U!
0T!
1f!
0e!
1<
1m!
1l!
0k!
b1100110011 G!
18
17
06
14
13
02
10
1/
0.
#240
0$
0<
#245
b10001000100010001000100010001000100010001000100010001000100010 )
b1000100010 *
1$
0-!
0)!
0%!
0!!
0{
0w
0s
0o
0k
0g
0c
0_
0[
0W
0S
0O
0K
0G
0C
1V!
0U!
1g!
0f!
1<
0m!
b1000100010 G!
08
04
00
#250
0$
0<
#255
b1000100001110111011001100101010101000100001100110010001000010001 )
b1100100001 *
1$
1-!
0,!
1%!
1!!
0~
1{
0z
1o
1k
0f
1e
0b
1a
1_
0^
1]
1[
0Z
1Y
1U
1Q
1O
1M
1K
1I
0F
1D
0B
1@
1W!
0V!
1h!
0g!
1<
1m!
0l!
b1100100001 G!
18
07
10
#260
0$
0<
#265
b1000100100010001100110100010001010101011001100111011110001000 )
b100100011 *
1$
1,!
0$!
0!!
1|
0{
1x
1w
1u
1s
1q
0o
1m
0k
1i
1g
1c
0_
0[
1W
0U
1S
0Q
0O
0M
0K
0I
1G
0D
1C
0@
1X!
0W!
1i!
0h!
1<
0m!
b100100011 G!
17
0/
#270
0$
0<
#275
b1000100010001000100010001000100010001000100010001000100010001000 )
b100010001000 *
1$
0-!
0,!
1*!
0(!
1&!
0%!
1"!
0w
0v
0u
1t
0s
0r
0q
1p
0n
0m
1l
0j
0i
1h
0g
0e
1d
0c
0a
1`
0]
1\
0Y
1X
0W
0V
1T
0S
0R
1P
0N
1L
0J
1H
0G
1D
0C
1@
0X!
1P!
0i!
1a!
1<
1j!
b100010001000 G!
08
07
15
03
11
00
1-
#280
0$
0<
#285
b1010101010101010101010101010101010101010101010101010101010101010 )
b100110011001 *
1$
1-!
1)!
1%!
1~
1z
1v
1r
1n
1j
1f
1b
1^
1Z
1V
1R
1N
1J
1F
1B
0P!
1O!
0a!
1`!
1<
1m!
b100110011001 G!
18
14
10
#290
0$
0<
#295
b1011101110111011101110111011101110111011101110111011101110111011 )
b101010101010 *
1$
0-!
1,!
0)!
1(!
0%!
1$!
1!!
1{
1w
1s
1o
1k
1g
1c
1_
1[
1W
1S
1O
1K
1G
1C
0O!
1N!
0`!
1_!
1<
0m!
1l!
b101010101010 G!
08
17
04
13
00
1/
#300
0$
0<
#305
b1100110011001100110011001100110011001100110011001100110011001100 )
b101110111011 *
1$
1-!
1)!
1%!
0!!
0~
1}
0{
0z
1y
0w
0v
1u
0s
0r
1q
0o
0n
1m
0k
0j
1i
0g
0f
1e
0c
0b
1a
0_
0^
1]
0[
0Z
1Y
0W
0V
1U
0S
0R
1Q
0O
0N
1M
0K
0J
1I
0G
0F
1E
0C
0B
1A
0N!
1M!
0_!
1^!
1<
1m!
b101110111011 G!
18
14
10
#310
0$
0<
#315
b1101110111011101110111011101110111011101110111011101110111011101 )
b110011001100 *
1$
0-!
0,!
1+!
0)!
0(!
1'!
0%!
0$!
1#!
1!!
1{
1w
1s
1o
1k
1g
1c
1_
1[
1W
1S
1O
1K
1G
1C
0M!
1L!
0^!
1]!
1<
0m!
0l!
1k!
b110011001100 G!
08
07
16
04
03
12
00
0/
1.
#320
0$
0<
#325
b1110111011101110111011101110111011101110111011101110111011101110 )
b110111011101 *
1$
1-!
1)!
1%!
0!!
1~
0{
1z
0w
1v
0s
1r
0o
1n
0k
1j
0g
1f
0c
1b
0_
1^
0[
1Z
0W
1V
0S
1R
0O
1N
0K
1J
0G
1F
0C
1B
0L!
1K!
0]!
1\!
1<
1m!
b110111011101 G!
18
14
10
#330
0$
0<
#335
b1111111111111111111111111111111111111111111111111111111111111111 )
b111011101110 *
1$
0-!
1,!
0)!
1(!
0%!
1$!
1!!
1{
1w
1s
1o
1k
1g
1c
1_
1[
1W
1S
1O
1K
1G
1C
0K!
1J!
0\!
1[!
1<
0m!
1l!
b111011101110 G!
08
17
04
13
00
1/
#340
0$
0<
#345
b1000100010001000100010001000100010001000100010001000100010001 )
b100010001 *
1$
1-!
0,!
0+!
0*!
1)!
0(!
0'!
0&!
1%!
0$!
0#!
0"!
0~
0}
0|
0z
0y
0x
0v
0u
0t
0r
0q
0p
0n
0m
0l
0j
0i
0h
0f
0e
0d
0b
0a
0`
0^
0]
0\
0Z
0Y
0X
0V
0U
0T
0R
0Q
0P
0N
0M
0L
0J
0I
0H
0F
0E
0D
0B
0A
0@
0J!
1I!
0[!
1Z!
1<
1m!
b100010001 G!
18
07
06
05
14
03
02
01
10
0/
0.
0-
